README.md
setup.cfg
setup.py
cont_prob_distributions/Binomialdistribution.py
cont_prob_distributions/Gaussiandistribution.py
cont_prob_distributions/Generaldistribution.py
cont_prob_distributions/__init__.py
cont_prob_distributions.egg-info/PKG-INFO
cont_prob_distributions.egg-info/SOURCES.txt
cont_prob_distributions.egg-info/dependency_links.txt
cont_prob_distributions.egg-info/not-zip-safe
cont_prob_distributions.egg-info/top_level.txt